[
  {
    "inputs": [
      {
        "internalType": "address",
        "name": "_invoiceTokenAddress",
        "type": "address"
      }
    ],
    "stateMutability": "nonpayable",
    "type": "constructor"
  },
  {
    "inputs": [
      {
        "internalType": "string",
        "name": "invoiceId",
        "type": "string"
      },
      {
        "internalType": "uint256",
        "name": "amount",
        "type": "uint256"
      }
    ],
    "name": "financeInvoice",
    "outputs": [],
    "stateMutability": "nonpayable",
    "type": "function"
  },
  {
    "inputs": [],
    "name": "invoiceToken",
    "outputs": [
      {
        "internalType": "contract InvoiceToken",
        "name": "",
        "type": "address"
      }
    ],
    "stateMutability": "view",
    "type": "function"
  },
  {
    "inputs": [
      {
        "internalType": "string",
        "name": "",
        "type": "string"
      }
    ],
    "name": "invoices",
    "outputs": [
      {
        "internalType": "uint256",
        "name": "amount",
        "type": "uint256"
      },
      {
        "internalType": "enum InvoiceFinancer.InvoiceStatus",
        "name": "status",
        "type": "uint8"
      },
      {
        "internalType": "address",
        "name": "financedBy",
        "type": "address"
      }
    ],
    "stateMutability": "view",
    "type": "function"
  },
  {
    "inputs": [
      {
        "internalType": "string",
        "name": "invoiceId",
        "type": "string"
      },
      {
        "internalType": "uint256",
        "name": "amount",
        "type": "uint256"
      }
    ],
    "name": "payInvoice",
    "outputs": [],
    "stateMutability": "nonpayable",
    "type": "function"
  }
]
